{
    "pools": [
        {
            "rolls": 1,
            "entries": [
                {
                    "type": "item",
                    "name": "iron_helmet",
                    "functions": [
                        {
                            "function": "enchant_with_levels",
                            "levels": {
                                "min": 15,
                                "max": 30
                            }
                        }
                    ]
                }
            ]
        }
    ]
}